appman/__init__.py
appman/cli.py
appman/config.py
appman/core.py
appman/log.py
appman/logs/__init__.py
appman/repo/.git/FETCH_HEAD
appman/repo/.git/HEAD
appman/repo/.git/ORIG_HEAD
appman/repo/.git/config
appman/repo/.git/description
appman/repo/.git/hooks/applypatch-msg.sample
appman/repo/.git/hooks/commit-msg.sample
appman/repo/.git/hooks/fsmonitor-watchman.sample
appman/repo/.git/hooks/post-update.sample
appman/repo/.git/hooks/pre-applypatch.sample
appman/repo/.git/hooks/pre-commit.sample
appman/repo/.git/hooks/pre-merge-commit.sample
appman/repo/.git/hooks/pre-push.sample
appman/repo/.git/hooks/pre-rebase.sample
appman/repo/.git/hooks/pre-receive.sample
appman/repo/.git/hooks/prepare-commit-msg.sample
appman/repo/.git/hooks/push-to-checkout.sample
appman/repo/.git/hooks/update.sample
appman/repo/.git/index
appman/repo/.git/info/exclude
appman/repo/.git/logs/HEAD
appman/repo/.git/logs/refs/heads/main
appman/repo/.git/logs/refs/remotes/origin/HEAD
appman/repo/.git/logs/refs/remotes/origin/main
appman/repo/.git/objects/02/e1ff5b19f2219a0c1d402e3026f11bf87f9498
appman/repo/.git/objects/07/8849aa95fa11ef6a192913913204a239ea043c
appman/repo/.git/objects/08/8075f3dfac48b9785da8476bef3cac9eca3bb3
appman/repo/.git/objects/0e/c45d256b0474b078aae48f64e1297eba365a67
appman/repo/.git/objects/13/6207f520d428694fc80c720d542517bc5389be
appman/repo/.git/objects/15/902255b9d3f5626258dabc00f594ec54f0ef2e
appman/repo/.git/objects/19/3281c973269ff721017e59abf265c8559349e6
appman/repo/.git/objects/19/84afb18b0c15f0ddd21609c68038b737fd3aad
appman/repo/.git/objects/1f/92765914d966f6fd4ed543de84016a51a3eadb
appman/repo/.git/objects/20/3d4f13deb343c8aa9f55bede4c91a27eac9136
appman/repo/.git/objects/20/72562c077f54d0cbc6eaa2b8e1f3da4cbafa89
appman/repo/.git/objects/21/4d4b88c0feee7dcbf45613f860d3fdb8bf3a28
appman/repo/.git/objects/23/3215dda68aafc9719738516d44a903742c99e9
appman/repo/.git/objects/23/e8274347cfd65fb12dc187fb1efaeb45c656b0
appman-0.4.5.dist-info/entry_points.txt
appman-0.4.5.dist-info/LICENSE
appman-0.4.5.dist-info/WHEEL
appman-0.4.5.dist-info/METADATA
appman-0.4.5.dist-info/RECORD
