Metadata-Version: 2.1
Name: appman
Version: 0.4.5
Summary: Cross-platform application management aggregator
Home-page: https://github.com/basiliskus/appman
License: MIT
Author: Basilio Bogado
Author-email: 541149+basiliskus@users.noreply.github.com
Requires-Python: >=3.9,<4.0
Classifier: License :: OSI Approved :: MIT License
Classifier: Programming Language :: Python :: 3
Classifier: Programming Language :: Python :: 3.10
Classifier: Programming Language :: Python :: 3.9
Requires-Dist: click (>=8.0.1,<9.0.0)
Requires-Dist: distro (>=1.5.0,<2.0.0)
Requires-Dist: importlib-resources (>=5.2.0,<6.0.0)
Requires-Dist: inquirerpy (>=0.3.4,<0.4.0)
Requires-Dist: pyyaml (>=5.3.1,<6.0.0)
Project-URL: Repository, https://github.com/basiliskus/appman.git
